vacuum_script.py
vacuum_git_cli-0.1.3.dist-info/METADATA
vacuum_git_cli-0.1.3.dist-info/WHEEL
vacuum_git_cli-0.1.3.dist-info/entry_points.txt
vacuum_git_cli-0.1.3.dist-info/top_level.txt
vacuum_git_cli-0.1.3.dist-info/RECORD
