Metadata-Version: 2.2
Name: vacuum-git-cli
Version: 0.1.3
Summary: A tool to clone specific folders from a Git repository
Home-page: https://github.com/Ayash-Bera/vaccum
Author: Ayash
Author-email: ayashbera@gmail.com
Classifier: Programming Language :: Python :: 3
Classifier: License :: OSI Approved :: MIT License
Classifier: Operating System :: OS Independent
Requires-Python: >=3.6
Dynamic: author
Dynamic: author-email
Dynamic: classifier
Dynamic: home-page
Dynamic: requires-python
Dynamic: summary
